pybrsa/__init__.py
pybrsa/data.py
pybrsa/fetch_bddk.py
pybrsa/fetch_finturk.py
pybrsa/info.py
pybrsa/io.py
pybrsa/utils.py
pybrsa/data/bddk_groups.csv
pybrsa/data/bddk_tables.csv
pybrsa/data/cities.csv
pybrsa/data/finturk_groups.csv
pybrsa/data/finturk_tables.csv
pybrsa-0.1.6.dist-info/licenses/LICENSE.md
pybrsa-0.1.6.dist-info/METADATA
pybrsa-0.1.6.dist-info/WHEEL
pybrsa-0.1.6.dist-info/top_level.txt
pybrsa-0.1.6.dist-info/RECORD
