Metadata-Version: 2.4
Name: pybrsa
Version: 0.1.6
Summary: Python package for fetching data from BDDK
Author-email: Ozan Bakis <your.email@example.com>
License-Expression: MIT
Project-URL: Homepage, https://github.com/obakis/pybrsa
Project-URL: Repository, https://github.com/obakis/pybrsa.git
Classifier: Programming Language :: Python :: 3.14
Requires-Python: >=3.9
License-File: LICENSE.md
Requires-Dist: pandas>=1.5.0
Requires-Dist: requests>=2.28.0
Requires-Dist: openpyxl>=3.0.0
Dynamic: license-file
